odoo/addons/multi_pms_properties/README.rst
odoo/addons/multi_pms_properties/__init__.py
odoo/addons/multi_pms_properties/__manifest__.py
odoo/addons/multi_pms_properties/models.py
odoo/addons/multi_pms_properties/i18n/it.po
odoo/addons/multi_pms_properties/i18n/multi_pms_properties.pot
odoo/addons/multi_pms_properties/readme/CONTRIBUTORS.rst
odoo/addons/multi_pms_properties/readme/DESCRIPTION.rst
odoo/addons/multi_pms_properties/readme/INSTALL.rst
odoo/addons/multi_pms_properties/readme/USAGE.rst
odoo/addons/multi_pms_properties/static/description/icon.png
odoo/addons/multi_pms_properties/static/description/index.html
odoo/addons/multi_pms_properties/tests/__init__.py
odoo/addons/multi_pms_properties/tests/common.py
odoo/addons/multi_pms_properties/tests/multi_pms_properties_tester.py
odoo/addons/multi_pms_properties/tests/test_multi_pms_properties.py
odoo14_addon_multi_pms_properties-14.0.1.0.1.dev8.dist-info/METADATA
odoo14_addon_multi_pms_properties-14.0.1.0.1.dev8.dist-info/WHEEL
odoo14_addon_multi_pms_properties-14.0.1.0.1.dev8.dist-info/top_level.txt
odoo14_addon_multi_pms_properties-14.0.1.0.1.dev8.dist-info/RECORD
